wikitopic/__init__.py
wikitopic/wikitopic.py
wikitopic-1.1.1.dist-info/LICENCE
wikitopic-1.1.1.dist-info/METADATA
wikitopic-1.1.1.dist-info/WHEEL
wikitopic-1.1.1.dist-info/top_level.txt
wikitopic-1.1.1.dist-info/RECORD
