Metadata-Version: 2.1
Name: wikitopic
Version: 1.1.1
Summary: Explicit online topic extraction for documents from Wikipedia
Home-page: https://github.com/ConKruG/wikitopic
Author: Arash Kia and Finbarr Murphy
Author-email: arash.nkia@gmail.com
License: GNU GPL v3.0
Platform: UNKNOWN
Requires-Dist: nltk
Requires-Dist: wikipedia
